external_markdown/plugin.py
mkdocs_embed_external_markdown_sd0408-2.1.6.dist-info/entry_points.txt
mkdocs_embed_external_markdown_sd0408-2.1.6.dist-info/LICENSE.md
mkdocs_embed_external_markdown_sd0408-2.1.6.dist-info/WHEEL
mkdocs_embed_external_markdown_sd0408-2.1.6.dist-info/METADATA
mkdocs_embed_external_markdown_sd0408-2.1.6.dist-info/RECORD
