Metadata-Version: 2.1
Name: mkdocs-embed-external-markdown-sd0408
Version: 2.1.6
Summary: Mkdocs plugin that allow to inject external markdown or markdown section from given url
Home-page: https://3os.org/guides/markdown-cheatsheet/external-markdown/
License: MIT
Keywords: mkdocs,plugin,markdown,external-markdown,embed,external,markdown-section
Author: fire1ce
Author-email: dev@3os.org
Requires-Python: >=3.6.2,<4.0.0
Classifier: License :: OSI Approved :: MIT License
Classifier: Programming Language :: Python :: 3
Classifier: Programming Language :: Python :: 3.7
Classifier: Programming Language :: Python :: 3.8
Classifier: Programming Language :: Python :: 3.9
Classifier: Programming Language :: Python :: 3.10
Requires-Dist: Jinja2 (>=3.0.3,<4.0.0)
Requires-Dist: requests (>=2.27.1,<3.0.0)
Project-URL: Repository, https://github.com/sd0408/mkdocs-embed-external-markdown
